pip_search_ex/__init__.py
pip_search_ex/p_s_e.py
pip_search_ex/core/__init__.py
pip_search_ex/core/colors.py
pip_search_ex/core/pypi.py
pip_search_ex/core/theme_loader.py
pip_search_ex/raw/__init__.py
pip_search_ex/raw/renderer.py
pip_search_ex/raw/table.py
pip_search_ex/themes/atom-one-dark.xml
pip_search_ex/themes/atom-one-light.xml
pip_search_ex/themes/catppuccin-latte.xml
pip_search_ex/themes/catppuccin-mocha.xml
pip_search_ex/themes/default.xml
pip_search_ex/themes/dracula.xml
pip_search_ex/themes/flexoki.xml
pip_search_ex/themes/gruvbox.xml
pip_search_ex/themes/monokai.xml
pip_search_ex/themes/none.xml
pip_search_ex/themes/nord.xml
pip_search_ex/themes/rose-pine-dawn.xml
pip_search_ex/themes/rose-pine-moon.xml
pip_search_ex/themes/rose-pine.xml
pip_search_ex/themes/solarized-dark.xml
pip_search_ex/themes/solarized-light.xml
pip_search_ex/themes/solarized.xml
pip_search_ex/themes/textual-ansi.xml
pip_search_ex/themes/textual-dark.xml
pip_search_ex/themes/textual-light.xml
pip_search_ex/themes/tokyo-night.xml
pip_search_ex/tui/__init__.py
pip_search_ex/tui/app.py
pip_search_ex-1.0.10.dist-info/licenses/LICENSE
pip_search_ex-1.0.10.dist-info/METADATA
pip_search_ex-1.0.10.dist-info/WHEEL
pip_search_ex-1.0.10.dist-info/entry_points.txt
pip_search_ex-1.0.10.dist-info/top_level.txt
pip_search_ex-1.0.10.dist-info/RECORD
