Metadata-Version: 2.4
Name: pip-search-ex
Version: 1.0.10
Summary: Extended pip search with TUI interface and package management
Author-email: thedwarf <python@dwarven.com>
Project-URL: Homepage, https://github.com/gitdwarf/pip-search-ex
Project-URL: Repository, https://github.com/gitdwarf/pip-search-ex
Project-URL: Bug Reports, https://github.com/gitdwarf/pip-search-ex/issues
Keywords: pip,search,package,manager,tui,terminal
Classifier: Development Status :: 4 - Beta
Classifier: Intended Audience :: Developers
Classifier: Topic :: Utilities
Classifier: License :: OSI Approved :: MIT License
Classifier: Programming Language :: Python :: 3
Classifier: Programming Language :: Python :: 3.8
Classifier: Programming Language :: Python :: 3.9
Classifier: Programming Language :: Python :: 3.10
Classifier: Programming Language :: Python :: 3.11
Classifier: Programming Language :: Python :: 3.12
Classifier: Environment :: Console
Requires-Python: >=3.8
License-File: LICENSE
Requires-Dist: requests>=2.25.0
Requires-Dist: wcwidth>=0.2.0
Requires-Dist: textual>=0.47.0
Requires-Dist: packaging>=20.0
Provides-Extra: dev
Requires-Dist: build; extra == "dev"
Requires-Dist: twine; extra == "dev"
Dynamic: license-file
